drawer/DrawerListener.py
drawer/SymbolTable.py
drawer/__init__.py
drawer/parser/Drawer.interp
drawer/parser/Drawer.tokens
drawer/parser/DrawerLexer.interp
drawer/parser/DrawerLexer.py
drawer/parser/DrawerLexer.tokens
drawer/parser/DrawerListener.py
drawer/parser/DrawerParser.py
drawerlang-1.0.1.dist-info/METADATA
drawerlang-1.0.1.dist-info/WHEEL
drawerlang-1.0.1.dist-info/RECORD
