Metadata-Version: 2.1
Name: drawerlang
Version: 1.0.1
Summary: 绘制脚本drawer的python实现
License: MIT
Author: chengmin
Author-email: cmtheit@naver.com
Requires-Python: >=3.10,<4.0
Classifier: License :: OSI Approved :: MIT License
Classifier: Programming Language :: Python :: 3
Classifier: Programming Language :: Python :: 3.10
Classifier: Programming Language :: Python :: 3.11
Classifier: Programming Language :: Python :: 3.12
Classifier: Programming Language :: Python :: 3.13
Requires-Dist: antlr4-python3-runtime (>=4.13.2,<5.0.0)
Requires-Dist: asyncio (>=3.4.3,<4.0.0)
Requires-Dist: webcolors (>=24.11.1,<25.0.0)
